MANIFEST.in
README.md
setup.cfg
setup.py
django_graphql_utils.egg-info/PKG-INFO
django_graphql_utils.egg-info/SOURCES.txt
django_graphql_utils.egg-info/dependency_links.txt
django_graphql_utils.egg-info/not-zip-safe
django_graphql_utils.egg-info/requires.txt
django_graphql_utils.egg-info/top_level.txt
graphql_utils/__init__.py
graphql_utils/admin.py
graphql_utils/apps.py
graphql_utils/models.py
graphql_utils/tests.py
graphql_utils/views.py
graphql_utils/migrations/__init__.py
graphql_utils/templates/graphql_utils/methods.js