Metadata-Version: 1.1
Name: django-graphql-utils
Version: 0.2
Summary: Utilities to work with Graphql in Django 
Home-page: https://github.com/synw/django-graphql-utils
Author: synw
Author-email: synwe@yahoo.com
License: UNKNOWN
Download-URL: https://github.com/synw/django-graphql-utils/releases/tag/0.2
Keywords: django,graphql
Platform: UNKNOWN
Classifier: Development Status :: 3 - Alpha
Classifier: Framework :: Django :: 1.11
Classifier: Intended Audience :: Developers
Classifier: License :: OSI Approved :: MIT License
Classifier: Programming Language :: Python :: 3.5
